py_actors/__init__.py
py_actors/actors.py
py_actors/control.py
py_actors/log_config.py
py_actors/micro_kernel.py
py_actors-0.0.6.dist-info/METADATA
py_actors-0.0.6.dist-info/RECORD
py_actors-0.0.6.dist-info/WHEEL
py_actors-0.0.6.dist-info/top_level.txt
