Metadata-Version: 2.1
Name: py-actors
Version: 0.0.6
Summary: Actor implementation in Python
Home-page: https://github.com/kmanc/py_actors
Author: Kevin Conley
Author-email: kmanc@comcast.net
License: MIT
Keywords: Python,Actor,Concurrency,Parallelism
Platform: UNKNOWN
Classifier: Development Status :: 5 - Production/Stable
Classifier: Topic :: Utilities
Requires-Python: >=3.6
